[
  {
    "id": "Q1",
    "question": "Знаете ли вы, что такое вектор?",
    "options": [
      "Да",
      "Примерно",
      "Нет"
    ],
    "counts": [
      18,
      10,
      2
    ]
  },
  {
    "id": "Q2",
    "question": "Где вы чаще всего встречаете слово «вектор»?",
    "options": [
      "Математика",
      "Физика",
      "Комп. графика",
      "Медицина",
      "Не встречаю"
    ],
    "counts": [
      17,
      6,
      3,
      2,
      2
    ]
  },
  {
    "id": "Q3",
    "question": "Что обязательно должно быть у векторной величины?",
    "options": [
      "Только величина",
      "Только направление",
      "Величина и направление",
      "Не знаю"
    ],
    "counts": [
      1,
      0,
      27,
      2
    ]
  },
  {
    "id": "Q4",
    "question": "Можно ли считать скорость векторной величиной?",
    "options": [
      "Да",
      "Нет",
      "Не уверен(а)"
    ],
    "counts": [
      23,
      2,
      5
    ]
  },
  {
    "id": "Q5",
    "question": "Можно ли считать температуру векторной величиной?",
    "options": [
      "Да",
      "Нет",
      "Не уверен(а)"
    ],
    "counts": [
      3,
      21,
      6
    ]
  },
  {
    "id": "Q6",
    "question": "Что такое результирующее перемещение?",
    "options": [
      "Сумма расстояний",
      "Вектор от начала к концу",
      "Среднее",
      "Не знаю"
    ],
    "counts": [
      6,
      21,
      1,
      2
    ]
  },
  {
    "id": "Q7",
    "question": "Где векторы полезны в жизни?",
    "options": [
      "Навигация",
      "Спорт",
      "Техника",
      "Комп. технологии",
      "Везде"
    ],
    "counts": [
      6,
      3,
      4,
      3,
      14
    ]
  },
  {
    "id": "Q8",
    "question": "Хотели бы больше примеров из жизни на уроках математики?",
    "options": [
      "Да",
      "Нет",
      "Иногда"
    ],
    "counts": [
      22,
      1,
      7
    ]
  }
]